petprep/__init__.py
petprep/__main__.py
petprep/_version.py
petprep/_warnings.py
petprep/config.py
petprep/conftest.py
petprep/cli/__init__.py
petprep/cli/parser.py
petprep/cli/run.py
petprep/cli/version.py
petprep/cli/workflow.py
petprep/cli/tests/__init__.py
petprep/cli/tests/test_parser.py
petprep/cli/tests/test_version.py
petprep/data/NOTICE
petprep/data/__init__.py
petprep/data/boilerplate.bib
petprep/data/io_spec.json
petprep/data/nipreps.json
petprep/data/reports-spec-anat.yml
petprep/data/reports-spec-func.yml
petprep/data/reports-spec-pet.yml
petprep/data/reports-spec.yml
petprep/data/flirtsch/bbr.sch
petprep/data/pvc/config.json
petprep/data/reference_mask/config.json
petprep/data/segmentation/__init__.py
petprep/data/segmentation/brainstem.txt
petprep/data/segmentation/hippocampus.txt
petprep/data/segmentation/raphe+pons.ctab
petprep/data/segmentation/raphe+pons.n21.d114.h5
petprep/data/segmentation/raphe+pons_cleaned.ctab
petprep/data/segmentation/sclimbic.ctab
petprep/data/segmentation/sclimbic_cleaned.ctab
petprep/data/tests/config.toml
petprep/data/tests/crash_files/crash-20170905-182839-root-dvars-b78e9ea8-e295-48a1-af71-2d36afd9cebf.txt
petprep/data/tests/ds000005/CHANGES
petprep/data/tests/ds000005/README
petprep/data/tests/ds000005/dataset_description.json
petprep/data/tests/ds000005/participants.tsv
petprep/data/tests/ds000005/task-mixedgamblestask_bold.json
petprep/data/tests/ds000005/sub-01/anat/sub-01_T1w.nii.gz
petprep/data/tests/ds000005/sub-01/anat/sub-01_inplaneT2.nii.gz
petprep/data/tests/ds000005/sub-01/pet/sub-01_pet.json
petprep/data/tests/ds000005/sub-01/pet/sub-01_pet.nii.gz
petprep/data/tests/logs/CITATION.html
petprep/interfaces/__init__.py
petprep/interfaces/bids.py
petprep/interfaces/cifti.py
petprep/interfaces/confounds.py
petprep/interfaces/conftest.py
petprep/interfaces/gifti.py
petprep/interfaces/maths.py
petprep/interfaces/patches.py
petprep/interfaces/pvc.py
petprep/interfaces/reference_mask.py
petprep-0.0.2.dist-info/METADATA
petprep-0.0.2.dist-info/WHEEL
petprep-0.0.2.dist-info/entry_points.txt
petprep-0.0.2.dist-info/licenses/LICENSE
petprep-0.0.2.dist-info/licenses/NOTICE
petprep-0.0.2.dist-info/RECORD
