Metadata-Version: 2.4
Name: petprep
Version: 0.0.2
Summary: A robust and easy-to-use pipeline for preprocessing of diverse PET data
Project-URL: Homepage, https://github.com/nipreps/petprep
Project-URL: Documentation, https://petprep.org
Project-URL: Paper, https://doi.org/10.1038/s41592-018-0235-4
Project-URL: Docker Images, https://hub.docker.com/r/nipreps/petprep/tags/
Project-URL: NiPreps, https://www.nipreps.org/
Author-email: The NiPreps Developers <nipreps@gmail.com>
License: 
License-File: LICENSE
License-File: NOTICE
Classifier: Development Status :: 5 - Production/Stable
Classifier: Intended Audience :: Science/Research
Classifier: License :: OSI Approved :: Apache Software License
Classifier: Programming Language :: Python :: 3.10
Classifier: Programming Language :: Python :: 3.11
Classifier: Programming Language :: Python :: 3.12
Classifier: Programming Language :: Python :: 3.13
Classifier: Topic :: Scientific/Engineering :: Image Recognition
Requires-Python: >=3.10
Requires-Dist: acres>=0.2.0
Requires-Dist: apscheduler>=3.10
Requires-Dist: codecarbon>=2
Requires-Dist: looseversion>=1.3
Requires-Dist: nibabel>=4.0.1
Requires-Dist: nipype>=1.8.5
Requires-Dist: nireports>=24.1.0
Requires-Dist: nitime>=0.9
Requires-Dist: nitransforms>=24.1.1
Requires-Dist: niworkflows>=1.14.1
Requires-Dist: numpy>=1.24
Requires-Dist: packaging>=24
Requires-Dist: pandas>=1.2
Requires-Dist: psutil>=5.4
Requires-Dist: pybids>=0.19.0
Requires-Dist: requests>=2.27
Requires-Dist: smriprep<0.19.0,>=0.17.0
Requires-Dist: tedana>=23.0.2
Requires-Dist: templateflow>=24.2.2
Requires-Dist: toml>=0.10
Requires-Dist: transforms3d>=0.4
Provides-Extra: all
Requires-Dist: coverage[toml]>=5.2.1; extra == 'all'
Requires-Dist: fuzzywuzzy; extra == 'all'
Requires-Dist: migas>=0.4.0; extra == 'all'
Requires-Dist: pydot>=1.2.3; extra == 'all'
Requires-Dist: pytest-cov>=2.11; extra == 'all'
Requires-Dist: pytest-env; extra == 'all'
Requires-Dist: pytest-xdist>=2.5; extra == 'all'
Requires-Dist: pytest>=8.1; extra == 'all'
Requires-Dist: python-levenshtein; extra == 'all'
Requires-Dist: sphinx-argparse!=0.5.0; extra == 'all'
Requires-Dist: sphinx-rtd-theme>=0.5.2; extra == 'all'
Requires-Dist: sphinx>=5; extra == 'all'
Provides-Extra: container
Requires-Dist: datalad; extra == 'container'
Requires-Dist: datalad-osf; extra == 'container'
Requires-Dist: migas>=0.4.0; extra == 'container'
Provides-Extra: dev
Requires-Dist: pre-commit; extra == 'dev'
Requires-Dist: ruff; extra == 'dev'
Provides-Extra: doc
Requires-Dist: pydot>=1.2.3; extra == 'doc'
Requires-Dist: sphinx-argparse!=0.5.0; extra == 'doc'
Requires-Dist: sphinx-rtd-theme>=0.5.2; extra == 'doc'
Requires-Dist: sphinx>=5; extra == 'doc'
Provides-Extra: docs
Requires-Dist: pydot>=1.2.3; extra == 'docs'
Requires-Dist: sphinx-argparse!=0.5.0; extra == 'docs'
Requires-Dist: sphinx-rtd-theme>=0.5.2; extra == 'docs'
Requires-Dist: sphinx>=5; extra == 'docs'
Provides-Extra: duecredit
Requires-Dist: duecredit; extra == 'duecredit'
Provides-Extra: maint
Requires-Dist: fuzzywuzzy; extra == 'maint'
Requires-Dist: python-levenshtein; extra == 'maint'
Provides-Extra: resmon
Provides-Extra: telemetry
Requires-Dist: migas>=0.4.0; extra == 'telemetry'
Provides-Extra: test
Requires-Dist: coverage[toml]>=5.2.1; extra == 'test'
Requires-Dist: pytest-cov>=2.11; extra == 'test'
Requires-Dist: pytest-env; extra == 'test'
Requires-Dist: pytest-xdist>=2.5; extra == 'test'
Requires-Dist: pytest>=8.1; extra == 'test'
Provides-Extra: tests
Requires-Dist: coverage[toml]>=5.2.1; extra == 'tests'
Requires-Dist: pytest-cov>=2.11; extra == 'tests'
Requires-Dist: pytest-env; extra == 'tests'
Requires-Dist: pytest-xdist>=2.5; extra == 'tests'
Requires-Dist: pytest>=8.1; extra == 'tests'
